{
  "salah_october":[

    {
      "day": "1",
      "sehri": "5:35",
      "fajrstart": "5:40",
      "fajrjamat": "6:30",
      "sunrise": "7:13",
      "zawal": "1:00",
      "zuhurstart": "1:06",
      "zuhurjamat": "1:45",
      "asrstart": "4:57",
      "asrjamat": "5:00",
      "magribstart": "6:57",
      "ishastart": "7:57",
      "ishaend": "8:15"
    },
    {
      "day": "2",
      "sehri": "5:36",
      "fajrstart": "5:41",
      "fajrjamat": "6:30",
      "sunrise": "7:15",
      "zawal": "1:00",
      "zuhurstart": "1:06",
      "zuhurjamat": "1:45",
      "asrstart": "4:55",
      "asrjamat": "5:00",
      "magribstart": "6:55",
      "ishastart": "7:55",
      "ishaend": "8:15"
    },
    {
      "day": "3",
      "sehri": "5:38",
      "fajrstart": "5:43",
      "fajrjamat": "6:30",
      "sunrise": "7:17",
      "zawal": "1:00",
      "zuhurstart": "1:06",
      "zuhurjamat": "1:45",
      "asrstart": "4:53",
      "asrjamat": "5:00",
      "magribstart": "6:53",
      "ishastart": "7:53",
      "ishaend": "8:15"
    },
    {
      "day": "4",
      "sehri": "5:39",
      "fajrstart": "5:44",
      "fajrjamat": "6:30",
      "sunrise": "7:18",
      "zawal": "12:59",
      "zuhurstart": "1:05",
      "zuhurjamat": "1:45",
      "asrstart": "4:51",
      "asrjamat": "5:00",
      "magribstart": "6:50",
      "ishastart": "7:50",
      "ishaend": "8:15"
    },
    {
      "day": "5",
      "sehri": "5:41",
      "fajrstart": "5:46",
      "fajrjamat": "6:30",
      "sunrise": "7:20",
      "zawal": "12:59",
      "zuhurstart": "1:05",
      "zuhurjamat": "1:45",
      "asrstart": "4:49",
      "asrjamat": "5:00",
      "magribstart": "6:48",
      "ishastart": "7:48",
      "ishaend": "8:15"
    },
    {
      "day": "6",
      "sehri": "5:42",
      "fajrstart": "5:47",
      "fajrjamat": "6:30",
      "sunrise": "7:22",
      "zawal": "12:59",
      "zuhurstart": "1:05",
      "zuhurjamat": "1:45",
      "asrstart": "4:47",
      "asrjamat": "5:00",
      "magribstart": "6:46",
      "ishastart": "7:46",
      "ishaend": "8:15"
    },
    {
      "day": "7",
      "sehri": "5:44",
      "fajrstart": "5:49",
      "fajrjamat": "6:30",
      "sunrise": "7:23",
      "zawal": "12:58",
      "zuhurstart": "1:04",
      "zuhurjamat": "1:45",
      "asrstart": "4:45",
      "asrjamat": "5:00",
      "magribstart": "6:44",
      "ishastart": "7:44",
      "ishaend": "8:15"
    },
    {
      "day": "8",
      "sehri": "5:46",
      "fajrstart": "5:51",
      "fajrjamat": "6:30",
      "sunrise": "7:25",
      "zawal": "12:58",
      "zuhurstart": "1:04",
      "zuhurjamat": "1:45",
      "asrstart": "4:43",
      "asrjamat": "5:00",
      "magribstart": "6:42",
      "ishastart": "7:42",
      "ishaend": "8:00"
    },
    {
      "day": "9",
      "sehri": "5:47",
      "fajrstart": "5:52",
      "fajrjamat": "6:30",
      "sunrise": "7:27",
      "zawal": "12:58",
      "zuhurstart": "1:04",
      "zuhurjamat": "1:45",
      "asrstart": "4:41",
      "asrjamat": "5:00",
      "magribstart": "6:37",
      "ishastart": "7:37",
      "ishaend": "8:00"
    },
    {
      "day": "10",
      "sehri": "5:49",
      "fajrstart": "5:54",
      "fajrjamat": "6:30",
      "sunrise": "7:28",
      "zawal": "12:58",
      "zuhurstart": "1:04",
      "zuhurjamat": "1:45",
      "asrstart": "4:39",
      "asrjamat": "5:00",
      "magribstart": "6:35",
      "ishastart": "7:35",
      "ishaend": "8:00"
    },
    {
      "day": "11",
      "sehri": "5:00",
      "fajrstart": "5:55",
      "fajrjamat": "6:45",
      "sunrise": "7:30",
      "zawal": "12:58",
      "zuhurstart": "1:04",
      "zuhurjamat": "1:45",
      "asrstart": "4:39",
      "asrjamat": "5:00",
      "magribstart": "6:33",
      "ishastart": "7:33",
      "ishaend": "8:00"
    },
    {
      "day": "12",
      "sehri": "5:52",
      "fajrstart": "5:57",
      "fajrjamat": "6:45",
      "sunrise": "7:32",
      "zawal": "12:57",
      "zuhurstart": "1:03",
      "zuhurjamat": "1:45",
      "asrstart": "4:37",
      "asrjamat": "5:00",
      "magribstart": "6:31",
      "ishastart": "7:31",
      "ishaend": "8:00"
    },
    {
      "day": "13",
      "sehri": "5:53",
      "fajrstart": "5:58",
      "fajrjamat": "6:45",
      "sunrise": "7:33",
      "zawal": "12:57",
      "zuhurstart": "1:03",
      "zuhurjamat": "1:45",
      "asrstart": "4:33",
      "asrjamat": "5:00",
      "magribstart": "6:28",
      "ishastart": "7:28",
      "ishaend": "8:00"
    },
    {
      "day": "14",
      "sehri": "5:55",
      "fajrstart": "6:00",
      "fajrjamat": "6:45",
      "sunrise": "7:35",
      "zawal": "12:57",
      "zuhurstart": "1:03",
      "zuhurjamat": "1:45",
      "asrstart": "4:31",
      "asrjamat": "5:00",
      "magribstart": "6:26",
      "ishastart": "7:26",
      "ishaend": "8:00"
    },
    {
      "day": "15",
      "sehri": "5:57",
      "fajrstart": "6:02",
      "fajrjamat": "6:45",
      "sunrise": "7:37",
      "zawal": "12:56",
      "zuhurstart": "1:02",
      "zuhurjamat": "1:45",
      "asrstart": "4:29",
      "asrjamat": "5:00",
      "magribstart": "6:24",
      "ishastart": "7:24",
      "ishaend": "8:00"
    },
    {
      "day": "16",
      "sehri": "5:58",
      "fajrstart": "6:03",
      "fajrjamat": "6:45",
      "sunrise": "7:38",
      "zawal": "12:56",
      "zuhurstart": "1:02",
      "zuhurjamat": "1:45",
      "asrstart": "4:27",
      "asrjamat": "5:00",
      "magribstart": "6:22",
      "ishastart": "7:22",
      "ishaend": "8:00"
    },
    {
      "day": "17",
      "sehri": "6:00",
      "fajrstart": "6:05",
      "fajrjamat": "6:45",
      "sunrise": "7:40",
      "zawal": "12:56",
      "zuhurstart": "1:02",
      "zuhurjamat": "1:45",
      "asrstart": "4:25",
      "asrjamat": "5:00",
      "magribstart": "6:20",
      "ishastart": "7:20",
      "ishaend": "8:00"
    },
    {
      "day": "18",
      "sehri": "6:02",
      "fajrstart": "6:07",
      "fajrjamat": "6:45",
      "sunrise": "7:42",
      "zawal": "12:56",
      "zuhurstart": "1:02",
      "zuhurjamat": "1:45",
      "asrstart": "4:23",
      "asrjamat": "5:00",
      "magribstart": "6:18",
      "ishastart": "7:18",
      "ishaend": "8:00"
    },
    {
      "day": "19",
      "sehri": "6:03",
      "fajrstart": "6:08",
      "fajrjamat": "6:45",
      "sunrise": "7:43",
      "zawal": "12:55",
      "zuhurstart": "1:01",
      "zuhurjamat": "1:45",
      "asrstart": "4:21",
      "asrjamat": "5:00",
      "magribstart": "6:16",
      "ishastart": "7:16",
      "ishaend": "8:00"
    },
    {
      "day": "20",
      "sehri": "6:05",
      "fajrstart": "6:10",
      "fajrjamat": "7:00",
      "sunrise": "7:45",
      "zawal": "12:55",
      "zuhurstart": "1:01",
      "zuhurjamat": "1:45",
      "asrstart": "4:19",
      "asrjamat": "5:00",
      "magribstart": "6:14",
      "ishastart": "7:14",
      "ishaend": "8:00"
    },
    {
      "day": "21",
      "sehri": "6:06",
      "fajrstart": "6:11",
      "fajrjamat": "7:00",
      "sunrise": "7:47",
      "zawal": "12:55",
      "zuhurstart": "1:01",
      "zuhurjamat": "1:45",
      "asrstart": "4:17",
      "asrjamat": "5:00",
      "magribstart": "6:12",
      "ishastart": "7:12",
      "ishaend": "8:00"
    },
    {
      "day": "22",
      "sehri": "6:08",
      "fajrstart": "6:13",
      "fajrjamat": "7:00",
      "sunrise": "7:49",
      "zawal": "12:55",
      "zuhurstart": "1:01",
      "zuhurjamat": "1:45",
      "asrstart": "4:16",
      "asrjamat": "5:00",
      "magribstart": "6:10",
      "ishastart": "7:10",
      "ishaend": "8:00"
    },
    {
      "day": "23",
      "sehri": "6:10",
      "fajrstart": "6:15",
      "fajrjamat": "7:00",
      "sunrise": "7:50",
      "zawal": "12:55",
      "zuhurstart": "1:01",
      "zuhurjamat": "1:45",
      "asrstart": "4:14",
      "asrjamat": "5:00",
      "magribstart": "6:08",
      "ishastart": "7:08",
      "ishaend": "8:00"
    },
    {
      "day": "24",
      "sehri": "6:11",
      "fajrstart": "6:16",
      "fajrjamat": "7:00",
      "sunrise": "7:52",
      "zawal": "12:55",
      "zuhurstart": "1:01",
      "zuhurjamat": "1:45",
      "asrstart": "4:12",
      "asrjamat": "5:00",
      "magribstart": "6:06",
      "ishastart": "7:06",
      "ishaend": "8:00"
    },
    {
      "day": "25",
      "sehri": "6:13",
      "fajrstart": "5:18",
      "fajrjamat": "7:00",
      "sunrise": "7:54",
      "zawal": "12:55",
      "zuhurstart": "1:01",
      "zuhurjamat": "1:45",
      "asrstart": "4:10",
      "asrjamat": "5:00",
      "magribstart": "6:04",
      "ishastart": "7:29",
      "ishaend": "8:00"
    },
    {
      "day": "26",
      "sehri": "6:15",
      "fajrstart": "6:20",
      "fajrjamat": "7:00",
      "sunrise": "7:56",
      "zawal": "12:54",
      "zuhurstart": "1:00",
      "zuhurjamat": "1:45",
      "asrstart": "4:08",
      "asrjamat": "5:00",
      "magribstart": "6:02",
      "ishastart": "7:27",
      "ishaend": "8:00"
    },
    {
      "day": "27",
      "sehri": "6:16",
      "fajrstart": "6:21",
      "fajrjamat": "7:00",
      "sunrise": "7:57",
      "zawal": "12:54",
      "zuhurstart": "1:00",
      "zuhurjamat": "1:45",
      "asrstart": "4:06",
      "asrjamat": "5:00",
      "magribstart": "6:00",
      "ishastart": "7:26",
      "ishaend": "8:00"
    },
    {
      "day": "28",
      "sehri": "6:18",
      "fajrstart": "6:23",
      "fajrjamat": "7:00",
      "sunrise": "7:59",
      "zawal": "12:54",
      "zuhurstart": "1:00",
      "zuhurjamat": "1:45",
      "asrstart": "4:05",
      "asrjamat": "5:00",
      "magribstart": "5:58",
      "ishastart": "7:24",
      "ishaend": "8:00"
    },
    {
      "day": "29",
      "sehri": "6:20",
      "fajrstart": "6:25",
      "fajrjamat": "7:00",
      "sunrise": "8:01",
      "zawal": "12:54",
      "zuhurstart": "1:00",
      "zuhurjamat": "1:45",
      "asrstart": "4:03",
      "asrjamat": "5:00",
      "magribstart": "5:56",
      "ishastart": "7:22",
      "ishaend": "8:00"
    },
    {
      "day": "30",
      "sehri": "6:21",
      "fajrstart": "6:26",
      "fajrjamat": "7:00",
      "sunrise": "8:03",
      "zawal": "12:54",
      "zuhurstart": "1:00",
      "zuhurjamat": "1:45",
      "asrstart": "4:01",
      "asrjamat": "5:00",
      "magribstart": "5:54",
      "ishastart": "7:21",
      "ishaend": "8:00"
    },
    {
      "day": "31",
      "sehri": "6:23",
      "fajrstart": "6:28",
      "fajrjamat": "7:00",
      "sunrise": "8:04",
      "zawal": "12:54",
      "zuhurstart": "1:00",
      "zuhurjamat": "1:45",
      "asrstart": "3:59",
      "asrjamat": "5:00",
      "magribstart": "5:52",
      "ishastart": "7:19",
      "ishaend": "8:00"
    }
  ]
}